darbiadev_fedex/__init__.py
darbiadev_fedex/fedex_services.py
darbiadev_fedex-0.3.0.dist-info/LICENSE
darbiadev_fedex-0.3.0.dist-info/WHEEL
darbiadev_fedex-0.3.0.dist-info/METADATA
darbiadev_fedex-0.3.0.dist-info/RECORD
