Metadata-Version: 2.1
Name: darbiadev-fedex
Version: 0.3.0
Summary: darbiadev-fedex
Home-page: https://github.com/darbiadev/darbiadev-fedex
License: MIT
Author: Bradley Reynolds
Author-email: bradley.reynolds@darbia.dev
Requires-Python: >=3.9,<4.0
Classifier: License :: OSI Approved :: MIT License
Classifier: Programming Language :: Python :: 3
Classifier: Programming Language :: Python :: 3.9
Provides-Extra: docs
Provides-Extra: tests
Requires-Dist: pytest (>=6.2.4,<7.0.0); extra == "tests"
Requires-Dist: requests (>=2.26.0,<3.0.0)
Requires-Dist: sphinx (>=4.1.1,<5.0.0); extra == "docs"
Requires-Dist: sphinx-autodoc-annotation (>=1.0-1,<2.0); extra == "docs"
Requires-Dist: sphinx-rtd-theme (>=0.5.2,<0.6.0); extra == "docs"
Requires-Dist: sphinxcontrib-apidoc (>=0.3.0,<0.4.0); extra == "docs"
Requires-Dist: sphinxcontrib-autoprogram (>=0.1.7,<0.2.0); extra == "docs"
Requires-Dist: sphinxcontrib-napoleon (>=0.7,<0.8); extra == "docs"
Requires-Dist: sphinxcontrib-packages (>=1.0.1,<2.0.0); extra == "docs"
Requires-Dist: toml (>=0.10.2,<0.11.0); extra == "docs"
Requires-Dist: tox (>=3.24.0,<4.0.0); extra == "tests"
Requires-Dist: xmltodict (>=0.12.0,<0.13.0)
Project-URL: Documentation, https://darbiadev.github.io/darbiadev-fedex/
Project-URL: Repository, https://github.com/darbiadev/darbiadev-fedex
